rl_games/.git/FETCH_HEAD
rl_games/.git/HEAD
rl_games/.git/ORIG_HEAD
rl_games/.git/config
rl_games/.git/description
rl_games/.git/hooks/applypatch-msg.sample
rl_games/.git/hooks/commit-msg.sample
rl_games/.git/hooks/fsmonitor-watchman.sample
rl_games/.git/hooks/post-update.sample
rl_games/.git/hooks/pre-applypatch.sample
rl_games/.git/hooks/pre-commit.sample
rl_games/.git/hooks/pre-merge-commit.sample
rl_games/.git/hooks/pre-push.sample
rl_games/.git/hooks/pre-rebase.sample
rl_games/.git/hooks/pre-receive.sample
rl_games/.git/hooks/prepare-commit-msg.sample
rl_games/.git/hooks/update.sample
rl_games/.git/index
rl_games/.git/info/exclude
rl_games/.git/logs/HEAD
rl_games/.git/logs/refs/heads/master
rl_games/.git/logs/refs/heads/real_tfinger
rl_games/.git/logs/refs/remotes/origin/HEAD
rl_games/.git/logs/refs/remotes/origin/master
rl_games/.git/logs/refs/remotes/origin/real_tfinger
rl_games/.git/objects/1b/8cb79243d15f5367053c2e0b6e08ee13486d2e
rl_games/.git/objects/1f/721147f878fdca9c3b5dfdcf11fc4194427580
rl_games/.git/objects/43/3062580fc20427e1c30d4ce22237ae2f2b89d5
rl_games/.git/objects/4d/a9a4a73904107f7f059bd22e1801c86e340477
rl_games/.git/objects/5d/d72011a4c6b902c268b53c53c8c2603ffb1b24
rl_games/.git/objects/61/2da962b3da4292ee4fa9a108f7c5d299141544
rl_games/.git/objects/62/c29b659cb952ec70f1b9d5af60b7cbb0cca540
rl_games/.git/objects/7e/42774f9165d4aa805bed4fe49a009ecd448cd8
rl_games/.git/objects/7e/f78f9e19649c9b3c47d1213b32250a9bf3e388
rl_games/.git/objects/83/9143ebf6fc1f117625473c0f843f5186fd5b4c
rl_games/.git/objects/83/aec7354373d7b6c357a7a726955dd04e575b99
rl_games/.git/objects/92/300cf5339afc007452ba03a6429fbac560beb7
rl_games/.git/objects/97/f9cf39e91a4d3ba0303f8d80f1bbf4bd791246
rl_games/.git/objects/ab/65a61e3067202668ed5e1a60fa5b99fce3d8fd
rl_games/.git/objects/b0/53a46f62fd3debd26a8086221ba4b0b53da81e
rl_games/.git/objects/b2/9f1dc53920d5d037dc88b0a7b82e5fbabb3e84
rl_games/.git/objects/b9/1b35812c7f646d24a738815f4688bd622addb6
rl_games_y-0.0.8.dist-info/LICENSE
rl_games_y-0.0.8.dist-info/METADATA
rl_games_y-0.0.8.dist-info/WHEEL
rl_games_y-0.0.8.dist-info/RECORD
